Metadata-Version: 2.1
Name: atlassian-tac
Version: 4.0.247
Summary: A tic-tac-toe library that supports different sizes and dimensions and how many marks in a row to win
Author: Silvanis Moody
Classifier: Intended Audience :: Developers
Classifier: Intended Audience :: Science/Research
Classifier: Programming Language :: Python :: 3
Classifier: License :: OSI Approved :: MIT License
Classifier: Operating System :: OS Independent
Classifier: Topic :: Games/Entertainment :: Turn Based Strategy
Classifier: Topic :: Software Development :: Libraries :: Python Modules
Requires-Python: >=3.6
License-File: LICENSE
Requires-Dist: numpy>=1.20
